rohan_pristine_sbert_v1/__init__.py
rohan_pristine_sbert_v1/embedder.py
rohan_pristine_sbert_v1-0.1.0.dist-info/licenses/LICENSE
tests/__init__.py
tests/test_embedder.py
rohan_pristine_sbert_v1-0.1.0.dist-info/METADATA
rohan_pristine_sbert_v1-0.1.0.dist-info/WHEEL
rohan_pristine_sbert_v1-0.1.0.dist-info/top_level.txt
rohan_pristine_sbert_v1-0.1.0.dist-info/RECORD
